spymock/__init__.py
spymock/spymock.py
spymock/utils.py
python_spymock-0.3.0.dist-info/LICENSE
python_spymock-0.3.0.dist-info/WHEEL
python_spymock-0.3.0.dist-info/METADATA
python_spymock-0.3.0.dist-info/RECORD
