Metadata-Version: 2.1
Name: python-spymock
Version: 0.3.0
Summary: 
Home-page: https://github.com/fixpoint/python-spymock
License: MIT
Author: lambdalisue
Author-email: lambdalisue@hashnote.net
Requires-Python: >=3.9,<4.0
Classifier: License :: OSI Approved :: MIT License
Classifier: Programming Language :: Python :: 3
Classifier: Programming Language :: Python :: 3.9
Project-URL: Repository, https://github.com/fixpoint/python-spymock
